metamorflite/__init__.py
Metamorf_Lite-0.0.0.dist-info/METADATA
Metamorf_Lite-0.0.0.dist-info/WHEEL
Metamorf_Lite-0.0.0.dist-info/top_level.txt
Metamorf_Lite-0.0.0.dist-info/RECORD
