Metadata-Version: 2.1
Name: Metamorf-Lite
Version: 0.0.0
Summary: Coming soon
Author-email: Guillermo Aumatell Salom <gaumatellsalom@gmail.com>
